LICENSE
README
setup.py
pypimc/__init__.py
pypimc.egg-info/PKG-INFO
pypimc.egg-info/SOURCES.txt
pypimc.egg-info/dependency_links.txt
pypimc.egg-info/requires.txt
pypimc.egg-info/top_level.txt