Metadata-Version: 2.1
Name: pypimc
Version: 1.1
Summary: Minecraft Information Library
Home-page: UNKNOWN
Author: Beete
Author-email: beete@protonmail.com
License: MIT
Keywords: Minecraft
Platform: UNKNOWN
License-File: LICENSE
